CONTRIBUTING.md
MANIFEST.in
README.rst
setup.py
docs/HISTORY.txt
docs/LICENSE.GPL
docs/LICENSE.txt
eea/__init__.py
eea.sentry.egg-info/PKG-INFO
eea.sentry.egg-info/SOURCES.txt
eea.sentry.egg-info/dependency_links.txt
eea.sentry.egg-info/entry_points.txt
eea.sentry.egg-info/namespace_packages.txt
eea.sentry.egg-info/not-zip-safe
eea.sentry.egg-info/requires.txt
eea.sentry.egg-info/top_level.txt
eea/sentry/README.txt
eea/sentry/__init__.py
eea/sentry/configure.zcml
eea/sentry/interfaces.py
eea/sentry/processors.py
eea/sentry/profiles.zcml
eea/sentry/setuphandlers.py
eea/sentry/version.txt
eea/sentry/browser/__init__.py
eea/sentry/browser/configure.zcml
eea/sentry/browser/sentry.py
eea/sentry/browser/js/bundle.tracing.min.js
eea/sentry/browser/js/sentry.js
eea/sentry/browser/zpt/sentry.pt
eea/sentry/locales/__init__.py
eea/sentry/locales/eea.pot
eea/sentry/locales/plone-manual.pot
eea/sentry/locales/update.sh
eea/sentry/locales/bg/LC_MESSAGES/eea.mo
eea/sentry/locales/bg/LC_MESSAGES/eea.po
eea/sentry/locales/bg/LC_MESSAGES/plone.mo
eea/sentry/locales/bg/LC_MESSAGES/plone.po
eea/sentry/locales/cs/LC_MESSAGES/eea.mo
eea/sentry/locales/cs/LC_MESSAGES/eea.po
eea/sentry/locales/cs/LC_MESSAGES/plone.mo
eea/sentry/locales/cs/LC_MESSAGES/plone.po
eea/sentry/locales/da/LC_MESSAGES/eea.mo
eea/sentry/locales/da/LC_MESSAGES/eea.po
eea/sentry/locales/da/LC_MESSAGES/plone.mo
eea/sentry/locales/da/LC_MESSAGES/plone.po
eea/sentry/locales/de/LC_MESSAGES/eea.mo
eea/sentry/locales/de/LC_MESSAGES/eea.po
eea/sentry/locales/de/LC_MESSAGES/plone.mo
eea/sentry/locales/de/LC_MESSAGES/plone.po
eea/sentry/locales/el/LC_MESSAGES/eea.mo
eea/sentry/locales/el/LC_MESSAGES/eea.po
eea/sentry/locales/el/LC_MESSAGES/plone.mo
eea/sentry/locales/el/LC_MESSAGES/plone.po
eea/sentry/locales/en/LC_MESSAGES/eea.mo
eea/sentry/locales/en/LC_MESSAGES/eea.po
eea/sentry/locales/en/LC_MESSAGES/plone.mo
eea/sentry/locales/en/LC_MESSAGES/plone.po
eea/sentry/locales/es/LC_MESSAGES/eea.mo
eea/sentry/locales/es/LC_MESSAGES/eea.po
eea/sentry/locales/es/LC_MESSAGES/plone.mo
eea/sentry/locales/es/LC_MESSAGES/plone.po
eea/sentry/locales/et/LC_MESSAGES/eea.mo
eea/sentry/locales/et/LC_MESSAGES/eea.po
eea/sentry/locales/et/LC_MESSAGES/plone.mo
eea/sentry/locales/et/LC_MESSAGES/plone.po
